zippyshare/__init__.py
zippyshare/api.py
zippyshare/core.py
zippyshare/filemanager.py
zippyshare/utils.py
zippyshare/__metadata__/LICENSE
zippyshare/__metadata__/README.md
zippyshare/__metadata__/__init__.py
zippyshare/__metadata__/requirements.txt
zippyshare-0.3.0.dist-info/METADATA
zippyshare-0.3.0.dist-info/WHEEL
zippyshare-0.3.0.dist-info/top_level.txt
zippyshare-0.3.0.dist-info/RECORD
