Metadata-Version: 2.1
Name: zippyshare
Version: 0.3.0
Summary: zippyshare complete API, CLI file manager, automatic account registration.
Home-page: https://github.com/foxe6/
Author: f̣ộx̣ệ6
Author-email: foxe6@protonmail.com
License: AGPL-3.0
Project-URL: Sourcecode, https://github.com/foxe6/zippyshare
Project-URL: Documentation, https://github.com/foxe6/zippyshare/blob/master/test
Project-URL: Example, https://github.com/foxe6/zippyshare/blob/master/zippyshare/example
Project-URL: Issues, https://github.com/foxe6/zippyshare/issues
Project-URL: Funding, https://paypal.me/foxe6
Project-URL: Say Thanks!, https://saythanks.io/to/foxe6
Keywords: zippyshare file host batch remote upload captcha recaptcha bypass account register registration api cli manager archive
Platform: UNKNOWN
Classifier: Programming Language :: Python :: 3.9
Classifier: Topic :: Utilities
Classifier: Natural Language :: English
Classifier: Intended Audience :: Developers
Classifier: License :: OSI Approved :: GNU Affero General Public License v3
Classifier: Operating System :: MacOS
Classifier: Operating System :: POSIX
Classifier: Operating System :: Microsoft :: Windows :: Windows 10
Classifier: Development Status :: 5 - Production/Stable
Requires-Python: >=3
Requires-Dist: lxml (>=0.0.1)
Requires-Dist: requests (>=0.0.1)
Requires-Dist: vpncmd (>=0.0.1)
Requires-Dist: sneaky (>=0.0.1)
Requires-Dist: omnitools (>=0.0.1)
Requires-Dist: aescipher (>=0.0.1)
Requires-Dist: easyrsa (>=0.0.1)
Requires-Dist: credsafe (>=0.0.1)
